{
  "items": [
    {
      "id": 1,
      "title": "Game 1",
      "image": "https://img.freepik.com/premium-photo/cyberpunk-gaming-controller-gamepad-joystick-illustration_691560-5812.jpg?size=338&ext=jpg&ga=GA1.1.1788068356.1717113600&semt=sph",
      "description": "This is a description of the game",
      "normalPrice": 10.00,
      "salePrice": 5.00,
      "releaseDate": "2020-01-01"
    },
    {
      "id": 2,
      "title": "Game 2",
      "image": "https://img.freepik.com/premium-photo/cyberpunk-gaming-controller-gamepad-joystick-illustration_691560-5812.jpg?size=338&ext=jpg&ga=GA1.1.1788068356.1717113600&semt=sph",
      "description": "This is a description of the game",
      "normalPrice": 10.00,
      "salePrice": 5.00,
      "releaseDate": "2020-01-01"
    },
    {
      "id": 3,
      "title": "Game 3",
      "image": "https://img.freepik.com/premium-photo/cyberpunk-gaming-controller-gamepad-joystick-illustration_691560-5812.jpg?size=338&ext=jpg&ga=GA1.1.1788068356.1717113600&semt=sph",
      "description": "This is a description of the game",
      "normalPrice": 10.00,
      "salePrice": 5.00,
      "releaseDate": "2020-01-01"
    },
    {
      "id": 4,
      "title": "Game 4",
      "image": "https://img.freepik.com/premium-photo/cyberpunk-gaming-controller-gamepad-joystick-illustration_691560-5812.jpg?size=338&ext=jpg&ga=GA1.1.1788068356.1717113600&semt=sph",
      "description": "This is a description of the game",
      "normalPrice": 10.00,
      "salePrice": 5.00,
      "releaseDate": "2020-01-01"
    },
    {
      "id": 5,
      "title": "Game 5",
      "image": "https://img.freepik.com/premium-photo/cyberpunk-gaming-controller-gamepad-joystick-illustration_691560-5812.jpg?size=338&ext=jpg&ga=GA1.1.1788068356.1717113600&semt=sph",
      "description": "This is a description of the game",
      "normalPrice": 10.00,
      "salePrice": 5.00,
      "releaseDate": "2020-01-01"
    },
    {
      "id": 6,
      "title": "Game 6",
      "image": "https://img.freepik.com/premium-photo/cyberpunk-gaming-controller-gamepad-joystick-illustration_691560-5812.jpg?size=338&ext=jpg&ga=GA1.1.1788068356.1717113600&semt=sph",
      "description": "This is a description of the game",
      "normalPrice": 10.00,
      "salePrice": 5.00,
      "releaseDate": "2020-01-01"
    },
    {
      "id": 7,
      "title": "Game 7",
      "image": "https://img.freepik.com/premium-photo/cyberpunk-gaming-controller-gamepad-joystick-illustration_691560-5812.jpg?size=338&ext=jpg&ga=GA1.1.1788068356.1717113600&semt=sph",
      "description": "This is a description of the game",
      "normalPrice": 10.00,
      "salePrice": 5.00,
      "releaseDate": "2020-01-01"
    },
    {
      "id": 8,
      "title": "Game 8",
      "image": "https://img.freepik.com/premium-photo/cyberpunk-gaming-controller-gamepad-joystick-illustration_691560-5812.jpg?size=338&ext=jpg&ga=GA1.1.1788068356.1717113600&semt=sph",
      "description": "This is a description of the game",
      "normalPrice": 10.00,
      "salePrice": 5.00,
      "releaseDate": "2020-01-01"
    }
  ]
}
